cllmv/__init__.py
cllmv/base.py
cllmv/pkg_hash.py
cllmv/lib/libcllmv.so
cllmv-0.1.1.dist-info/METADATA
cllmv-0.1.1.dist-info/WHEEL
cllmv-0.1.1.dist-info/top_level.txt
cllmv-0.1.1.dist-info/RECORD
