Metadata-Version: 2.1
Name: cllmv
Version: 0.1.1
Summary: Chutes fast LLM verification.
Home-page: https://github.com/chutesai/cllmv
Author: chutes.ai
Classifier: Development Status :: 3 - Alpha
Classifier: Intended Audience :: Developers
Classifier: Operating System :: POSIX :: Linux
Classifier: Programming Language :: Python :: 3
Classifier: Programming Language :: Python :: 3.10
Classifier: Programming Language :: Python :: 3.11
Classifier: Programming Language :: Python :: 3.12
Classifier: Programming Language :: Python :: 3 :: Only
Requires-Dist: setuptools>=0.75
Provides-Extra: dev
Requires-Dist: ruff; extra == "dev"
Requires-Dist: wheel; extra == "dev"
